abidcalculator/__init__.py
abidcalculator/calculator.py
abidcalculator-0.0.2.dist-info/METADATA
abidcalculator-0.0.2.dist-info/WHEEL
abidcalculator-0.0.2.dist-info/license
abidcalculator-0.0.2.dist-info/top_level.txt
abidcalculator-0.0.2.dist-info/RECORD
