Metadata-Version: 2.1
Name: abidcalculator
Version: 0.0.2
Summary: This is a very basic calculator and i am just trying to upload it, nothing more.....
Author: Abid Sahariar
Author-email: 1001128@daffodil.ac
License-File: license
